Metadata-Version: 2.1
Name: distributions-imokut
Version: 0.1
Summary: Gaussian and Binomial distributions
Author: Imokutmfon Udoh
Author-email: imokutofficial@gmail.com
License-File: LICENSE
